corally/__init__.py
corally/api/__init__.py
corally/api/free_server.py
corally/api/server.py
corally/cli/__init__.py
corally/cli/calculator.py
corally/cli/currency.py
corally/cli/main.py
corally/core/__init__.py
corally/core/calculator.py
corally/gui/__init__.py
corally/gui/launcher.py
corally/gui/main.py
corally-2.2.dist-info/licenses/LICENSE
corally-2.2.dist-info/METADATA
corally-2.2.dist-info/WHEEL
corally-2.2.dist-info/entry_points.txt
corally-2.2.dist-info/top_level.txt
corally-2.2.dist-info/RECORD
