Metadata-Version: 2.4
Name: corally
Version: 2.2
Summary: A comprehensive calculator suite with GUI and API support
Home-page: https://github.com/yourusername/corally
Author: Corally Team
Author-email: Corally Team <fleermaxim@gmail.com>
License: MIT
Project-URL: Homepage, https://github.com/mephisto-007
Project-URL: Documentation, https://github.com/mephisto-007/corally#readme
Project-URL: Repository, https://github.com/mephisto-007/Corally
Project-URL: Bug Tracker, https://github.com/mephisto-007/corally/issues
Keywords: calculator,currency,converter,interest,gui,api,finance,math,tkinter,fastapi
Classifier: Development Status :: 4 - Beta
Classifier: Intended Audience :: Developers
Classifier: Intended Audience :: Education
Classifier: Intended Audience :: End Users/Desktop
Classifier: License :: OSI Approved :: MIT License
Classifier: Operating System :: OS Independent
Classifier: Programming Language :: Python :: 3
Classifier: Programming Language :: Python :: 3.8
Classifier: Programming Language :: Python :: 3.9
Classifier: Programming Language :: Python :: 3.10
Classifier: Programming Language :: Python :: 3.11
Classifier: Programming Language :: Python :: 3.12
Classifier: Topic :: Office/Business :: Financial :: Spreadsheet
Classifier: Topic :: Scientific/Engineering :: Mathematics
Classifier: Topic :: Software Development :: Libraries :: Python Modules
Classifier: Topic :: Utilities
Requires-Python: >=3.8
License-File: LICENSE
Requires-Dist: fastapi>=0.68.0
Requires-Dist: uvicorn>=0.15.0
Requires-Dist: httpx>=0.24.0
Requires-Dist: requests>=2.25.0
Requires-Dist: python-dotenv>=0.19.0
Provides-Extra: gui
Requires-Dist: tkinter; extra == "gui"
Provides-Extra: dev
Requires-Dist: pytest>=6.0; extra == "dev"
Requires-Dist: pytest-cov; extra == "dev"
Requires-Dist: black; extra == "dev"
Requires-Dist: flake8; extra == "dev"
Requires-Dist: mypy; extra == "dev"
Requires-Dist: build; extra == "dev"
Requires-Dist: twine; extra == "dev"
Dynamic: author
Dynamic: home-page
Dynamic: license-file
Dynamic: requires-python
